{"results":[{"answers":["a"],"serial":1},{"answers":["b"],"serial":2},{"answers":["c"],"serial":3},{"answers":["d"],"serial":4},{"answers":["d"],"serial":5},{"answers":["c"],"serial":6},{"answers":["b"],"serial":7},{"answers":["a"],"serial":8},{"answers":["a"],"serial":9},{"answers":["b"],"serial":10},{"answers":["c"],"serial":11},{"answers":["d"],"serial":12},{"answers":[""],"question":13},{"answers":["d"],"serial":14},{"answers":[""],"question":15},{"answers":["c"],"serial":16},{"answers":["c"],"serial":17},{"answers":["b"],"serial":18},{"answers":[""],"question":19},{"answers":["a"],"serial":20},{"answers":["a"],"serial":21},{"answers":["a"],"serial":22},{"answers":["a"],"serial":23},{"answers":["b"],"serial":24},{"answers":[""],"question":25},{"answers":["c"],"serial":26},{"answers":["c"],"serial":27},{"answers":["d"],"serial":28},{"answers":["d"],"serial":29},{"answers":[""],"question":30},{"answers":[""],"question":31},{"answers":[""],"question":32},{"answers":[""],"question":33},{"answers":[""],"question":34},{"answers":[""],"question":35},{"answers":[""],"question":36},{"answers":[""],"question":37},{"answers":[""],"question":38},{"answers":["a"],"serial":39},{"answers":["b"],"serial":26},{"answers":["c"],"serial":27},{"answers":["d"],"serial":28},{"answers":["d"],"serial":29},{"answers":["c"],"serial":30},{"answers":["b"],"serial":31},{"answers":["a"],"serial":32},{"answers":["a"],"serial":33},{"answers":["b"],"serial":34},{"answers":["c"],"serial":35},{"answers":["d"],"serial":36},{"answers":["d"],"serial":37},{"answers":["d"],"serial":38},{"answers":["d"],"serial":39},{"answers":["c"],"serial":40},{"answers":["c"],"serial":41},{"answers":["b"],"serial":42},{"answers":["b"],"serial":43},{"answers":["b"],"serial":44},{"answers":["b"],"serial":45},{"answers":[""],"question":46},{"answers":["c"],"serial":47},{"answers":["c"],"serial":48},{"answers":["d"],"serial":49},{"answers":["d"],"serial":50},{"answers":["d"],"serial":51},{"answers":["d"],"serial":52},{"answers":[""],"question":53},{"answers":["c"],"serial":54},{"answers":["c"],"serial":55},{"answers":[""],"question":56},{"answers":[""],"question":57},{"answers":["a"],"serial":58},{"answers":["a"],"serial":59},{"answers":["b"],"serial":60},{"answers":["b"],"serial":61},{"answers":[""],"question":62},{"answers":["c"],"serial":63},{"answers":["c"],"serial":51},{"answers":["b"],"serial":52},{"answers":["a"],"serial":53},{"answers":["a"],"serial":54},{"answers":["b"],"serial":55},{"answers":["c"],"serial":56},{"answers":["d"],"serial":57},{"answers":["d"],"serial":58},{"answers":["d"],"serial":59},{"answers":["d"],"serial":60},{"answers":["c"],"serial":61},{"answers":["b"],"serial":62},{"answers":["b"],"serial":63},{"answers":["a"],"serial":64},{"answers":["a"],"serial":65},{"answers":["a"],"serial":66},{"answers":["a"],"serial":67},{"answers":["b"],"serial":68},{"answers":["b"],"serial":69},{"answers":["c"],"serial":70},{"answers":["c"],"serial":71},{"answers":["c"],"serial":72},{"answers":["c"],"serial":73},{"answers":["c"],"serial":74},{"answers":["c"],"serial":75},{"answers":["b"],"serial":76},{"answers":["b"],"serial":77},{"answers":[""],"question":78},{"answers":[""],"question":79},{"answers":["a"],"serial":80},{"answers":["a"],"serial":81},{"answers":["b"],"serial":82},{"answers":["b"],"serial":83},{"answers":["c"],"serial":84},{"answers":["c"],"serial":85},{"answers":["d"],"serial":86},{"answers":["d"],"serial":87},{"answers":["d"],"serial":88},{"answers":[""],"question":89},{"answers":["c"],"serial":90},{"answers":["d"],"serial":76},{"answers":["c"],"serial":77},{"answers":["b"],"serial":78},{"answers":["a"],"serial":79},{"answers":["a"],"serial":80},{"answers":["a"],"serial":81},{"answers":["b"],"serial":82},{"answers":["c"],"serial":83},{"answers":["d"],"serial":84},{"answers":["d"],"serial":85},{"answers":["d"],"serial":86},{"answers":["d"],"serial":87},{"answers":["c"],"serial":88},{"answers":["c"],"serial":89},{"answers":["b"],"serial":90},{"answers":["b"],"serial":91},{"answers":["a"],"serial":92},{"answers":["a"],"serial":93},{"answers":["a"],"serial":94},{"answers":["a"],"serial":95},{"answers":["b"],"serial":96},{"answers":["b"],"serial":97},{"answers":["c"],"serial":98},{"answers":["c"],"serial":99},{"answers":["d"],"serial":100},{"answers":["d"],"serial":101},{"answers":["d"],"serial":102},{"answers":["d"],"serial":103},{"answers":["d"],"serial":104},{"answers":["c"],"serial":105},{"answers":["c"],"serial":106},{"answers":["b"],"serial":107},{"answers":["b"],"serial":108},{"answers":["a"],"serial":109},{"answers":["a"],"serial":110},{"answers":[""],"serial":111},{"answers":["b"],"serial":112},{"answers":["b"],"serial":113},{"answers":[""],"question":114},{"answers":["c"],"serial":115},{"answers":["c"],"serial":116}],"status":false,"imageName":"Image_001.jpg"}